{
  "offerings": [
    {
      "id": 1,
      "description": "  Nappies",
      "icon": "cil-child-friends"
    },
    {
      "id": 2,
      "description": "No charge on public holidays",
      "icon": "cil-child-friendly"
    },
    {
      "id": 3,
      "description": "Storypark",
      "icon": "cil-child-friendly"
    },
    {
      "id": 4,
      "description": "Age appropriate toys and books",
      "icon": "cil-child-friendly"
    },
    {
      "id": 5,
      "description": "Sunscreen",
      "icon": "cil-child-friendly"
    },
    {
      "id": 6,
      "description": "Nappies",
      "icon": "cil-child-friendly"
    },
    {
      "id": 7,
      "description": "All meals",
      "icon": "cil-child-friendly"
    },
    {
      "id": 8,
      "description": "Qualified and dedicated early childhood carers",
      "icon": "cil-child-friendly"
    },
    {
      "id": 9,
      "description": "Extra curricular activities",
      "icon": "cil-child-friendly"
    },
    {
      "id": 10,
      "description": "Morning pickup",
      "icon": "morning-pickup"
    },
    {
      "id": 11,
      "description": "Afternoon pickup",
      "icon": "afternoon-pickup"
    }
  ],
  "centres": [
    {
      "id": 1,
      "name": "Amazing Centre",
      "address": "5 Smith Street",
      "suburb": "Brisbane",
      "postcode": "4000",
      "state": "QLD",
      "country": "Australia",
      "phone": "1800 000 0555",
      "lat": -27.253,
      "long": 153.078,
      "description": "I am very pretty.",
      "nqsrating": "Excellent",
      "email": "amazingcentre@amazing.centre",
      "offering": [
        1,
        4,
        7,
        9,
        6,
        2,
        8,
        3
      ],
      "photos": [
        {
          "id": 1,
          "fileUrl": "assets/img/centres/image1.jpg",
          "fileType": "jpg",
          "isMain": true,
          "sequence": 1
        },
        {
          "id": 2,
          "fileUrl": "assets/img/centres/image2.jpg",
          "fileType": "jpg",
          "isMain": true,
          "sequence": 1
        },
        {
          "id": 3,
          "fileUrl": "assets/img/centres/image3.jpg",
          "fileType": "jpg",
          "isMain": true,
          "sequence": 1
        },
        {
          "id": 4,
          "fileUrl": "assets/img/centres/image4.jpg",
          "fileType": "jpg",
          "isMain": true,
          "sequence": 1
        }
      ],
      "opening": [
        {
          "id": 1,
          "day": "Monday",
          "openingtime": "6:00AM",
          "closingtime": "5:00PM"
        }
      ]
    },
    {
      "id": 2,
      "name": "Albert Centre",
      "address": "55 Smith Street",
      "suburb": "Carina",
      "postcode": "4019",
      "state": "QLD",
      "country": "Australia",
      "phone": "1800 000 0555",
      "lat": -27.233187156915747,
      "long": 153.10126797,
      "description": "xxxx",
      "nqsrating": "Excellent",
      "email": "xxx",
      "offering": [
        1,
        4,
        6,
        2,
        8,
        3,
        5,
        7
      ],
      "photos": [
        {
          "id": 1,
          "fileUrl": "assets/img/centres/image1.jpg",
          "fileType": "jpg",
          "isMain": true,
          "sequence": 1
        },
        {
          "id": 2,
          "fileUrl": "assets/img/centres/image2.jpg",
          "fileType": "jpg",
          "isMain": true,
          "sequence": 1
        },
        {
          "id": 3,
          "fileUrl": "assets/img/centres/image3.jpg",
          "fileType": "jpg",
          "isMain": true,
          "sequence": 1
        },
        {
          "id": 4,
          "fileUrl": "assets/img/centres/image4.jpg",
          "fileType": "jpg",
          "isMain": true,
          "sequence": 1
        }
      ],
      "opening": [
        {
          "id": 1,
          "day": "Monday",
          "openingtime": "6:00AM",
          "closingtime": "5:00PM"
        }
      ]
    },
    {
      "id": 3,
      "name": "Sebastian Centre",
      "address": "5 Smith Street",
      "suburb": "x",
      "postcode": "x",
      "state": "x",
      "country": "x",
      "phone": "1800 000 0555",
      "lat": 555.2,
      "long": 555.1,
      "description": "xxxx",
      "nqsrating": "xx",
      "email": "xxx",
      "offering": [
        1,
        2,
        3,
        4,
        5
      ],
      "photos": [
        {
          "id": 1,
          "fileUrl": "assets/img/centres/image1.jpg",
          "fileType": "jpg",
          "isMain": true,
          "sequence": 1
        },
        {
          "id": 2,
          "fileUrl": "assets/img/centres/image2.jpg",
          "fileType": "jpg",
          "isMain": true,
          "sequence": 1
        },
        {
          "id": 3,
          "fileUrl": "assets/img/centres/image3.jpg",
          "fileType": "jpg",
          "isMain": true,
          "sequence": 1
        },
        {
          "id": 4,
          "fileUrl": "assets/img/centres/image4.jpg",
          "fileType": "jpg",
          "isMain": true,
          "sequence": 1
        }
      ],
      "opening": [
        {
          "id": 1,
          "day": "Monday",
          "openingtime": "6:00AM",
          "closingtime": "5:00PM"
        }
      ]
    }
  ],
  "rooms": [
    {
      "id": 1,
      "roomName": ""
    },
    {
      "id": 2,
      "centreId": 1,
      "roomName": " Nursery",
      "minAge": "35",
      "maxAge": "45",
      "childRatio": "1",
      "staffRatio": "4",
      "capacity": "4",
      "dailyRate": "95.00",
      "name": " Nursery"
    },
    {
      "id": 6,
      "centreId": 2,
      "roomName": "Nursery",
      "minAge": "0",
      "maxAge": "12",
      "childRatio": "1",
      "staffRatio": "4",
      "capacity": "4",
      "dailyRate": "95.00",
      "name": "Nursery"
    },
    {
      "id": 7,
      "centreId": 2,
      "roomName": "Toddlers A",
      "minAge": "0",
      "maxAge": "12",
      "childRatio": "1",
      "staffRatio": "5",
      "capacity": "4",
      "dailyRate": "95.00",
      "name": "Kindergarten A"
    },
    {
      "id": 8,
      "centreId": 2,
      "roomName": "Toddlers B",
      "minAge": "0",
      "maxAge": "12",
      "childRatio": "1",
      "staffRatio": "4",
      "capacity": "4",
      "dailyRate": "95.00",
      "name": "Kindergarten B"
    },
    {
      "id": 9,
      "centreId": 2,
      "roomName": "Kindergarten",
      "minAge": "0",
      "maxAge": "12",
      "childRatio": "1",
      "staffRatio": "4",
      "capacity": "4",
      "dailyRate": "95.00",
      "name": "Pre-kindergarten"
    },
    {
      "id": 10,
      "roomName": "NurseryNurseryNursery",
      "minAge": "0",
      "maxAge": "10",
      "childRatio": "1",
      "staffRatio": "5",
      "capacity": "4",
      "dailyRate": "95"
    },
    {
      "id": 11,
      "roomName": "Kinder",
      "minAge": "0",
      "maxAge": "5",
      "childRatio": ""
    },
    {
      "id": 12,
      "roomName": "Test",
      "minAge": "0",
      "maxAge": "11",
      "childRatio": "1",
      "staffRatio": "1",
      "capacity": "1",
      "dailyRate": "1"
    },
    {
      "id": 15,
      "name": "X",
      "minAge": "X",
      "maxAge": "X",
      "childRatio": "X",
      "staffRatio": "X",
      "capacity": "X",
      "dailyRate": "X"
    },
    {
      "id": 16,
      "name": " Toddlers A",
      "minAge": "25",
      "maxAge": "35",
      "childRatio": "1",
      "staffRatio": "5",
      "capacity": "5",
      "dailyRate": "99.00",
      "centreId": 1
    },
    {
      "id": 17,
      "name": "Toddlers B",
      "minAge": "25",
      "maxAge": "35",
      "childRatio": "1",
      "staffRatio": "5",
      "capacity": "5",
      "dailyRate": "99.00",
      "centreId": 1
    },
    {
      "id": 18,
      "name": "Pre-Kindergarten A",
      "minAge": "35",
      "maxAge": "72",
      "childRatio": "1",
      "staffRatio": "6",
      "capacity": "6",
      "dailyRate": "99.00",
      "centreId": 1
    },
    {
      "id": 20,
      "name": "Toddlers",
      "minAge": "1",
      "maxAge": "5",
      "childRatio": "1",
      "staffRatio": "5",
      "capacity": "5",
      "dailyRate": "95",
      "centreId": 2
    },
    {
      "id": 21,
      "name": "Kindergarten",
      "minAge": "36",
      "maxAge": "72",
      "childRatio": "1",
      "staffRatio": "12",
      "capacity": "12",
      "dailyRate": "55",
      "centreId": 1
    }
  ],
  "children": [
    {
      "id": 1,
      "firstName": "Nani",
      "lastName": "Axford",
      "dob": "2019-03-29",
      "crn": "978030450-9"
    },
    {
      "id": 2,
      "firstName": "Cari",
      "lastName": "Guilder",
      "dob": "2019-11-15",
      "crn": "585038300-X"
    },
    {
      "id": 3,
      "firstName": "Tedd",
      "lastName": "Robertot",
      "dob": "2018-07-05",
      "crn": "675974792-5"
    },
    {
      "id": 4,
      "firstName": "Charmane",
      "lastName": "Kennealy",
      "dob": "2019-03-08",
      "crn": "372375656-5"
    },
    {
      "id": 5,
      "firstName": "Andrea",
      "lastName": "Rixon",
      "dob": "2019-08-27",
      "crn": "084126291-8"
    },
    {
      "id": 6,
      "firstName": "Ernaline",
      "lastName": "Chaundy",
      "dob": "2020-06-03",
      "crn": "890965846-0"
    },
    {
      "id": 7,
      "firstName": "Beniamino",
      "lastName": "Pickle",
      "dob": "2018-11-02",
      "crn": "151086803-8"
    },
    {
      "id": 8,
      "firstName": "Patin",
      "lastName": "Corragan",
      "dob": "2019-04-26",
      "crn": "308202057-7"
    },
    {
      "id": 9,
      "firstName": "Harriott",
      "lastName": "Kretschmer",
      "dob": "2019-06-20",
      "crn": "452517291-6"
    },
    {
      "id": 10,
      "firstName": "Gill",
      "lastName": "Vanacci",
      "dob": "2019-06-08",
      "crn": "400097732-6"
    },
    {
      "id": 11,
      "firstName": "Morna",
      "lastName": "Peiser",
      "dob": "2020-12-09",
      "crn": "722378903-4"
    },
    {
      "id": 12,
      "firstName": "Winnie",
      "lastName": "Langfield",
      "dob": "2018-07-28",
      "crn": "792662774-7"
    },
    {
      "id": 13,
      "firstName": "Chase",
      "lastName": "Bolwell",
      "dob": "2020-11-19",
      "crn": "773008988-2"
    },
    {
      "id": 14,
      "firstName": "Natalya",
      "lastName": "Zaple",
      "dob": "2021-01-28",
      "crn": "594574919-2"
    },
    {
      "id": 15,
      "firstName": "Alon",
      "lastName": "Tonry",
      "dob": "2019-03-14",
      "crn": "421555670-8"
    },
    {
      "id": 16,
      "firstName": "Cassandre",
      "lastName": "Kures",
      "dob": "2021-03-20",
      "crn": "596922853-2"
    },
    {
      "id": 17,
      "firstName": "Fania",
      "lastName": "Rigmond",
      "dob": "2019-08-21",
      "crn": "012234977-6"
    },
    {
      "id": 18,
      "firstName": "Stacey",
      "lastName": "Kemwal",
      "dob": "2019-11-07",
      "crn": "515219618-2"
    },
    {
      "id": 19,
      "firstName": "Collen",
      "lastName": "Spellicy",
      "dob": "2018-12-14",
      "crn": "965280831-8"
    },
    {
      "id": 20,
      "firstName": "Skylar",
      "lastName": "O'Henehan",
      "dob": "2019-07-14",
      "crn": "982672951-5"
    },
    {
      "id": 21,
      "firstName": "Hedvige",
      "lastName": "Garmans",
      "dob": "2020-11-10",
      "crn": "605345075-8"
    },
    {
      "id": 22,
      "firstName": "Rasla",
      "lastName": "Axleby",
      "dob": "2020-10-09",
      "crn": "353043735-2"
    },
    {
      "id": 23,
      "firstName": "Licha",
      "lastName": "Warder",
      "dob": "2020-06-07",
      "crn": "103902096-8"
    },
    {
      "id": 24,
      "firstName": "Niki",
      "lastName": "Fremantle",
      "dob": "2019-10-06",
      "crn": "151421768-6"
    },
    {
      "id": 25,
      "firstName": "Tove",
      "lastName": "Addenbrooke",
      "dob": "2020-09-15",
      "crn": "092149894-2"
    },
    {
      "id": 26,
      "firstName": "Rufe",
      "lastName": "Pes",
      "dob": "2018-12-20",
      "crn": "317311124-9"
    },
    {
      "id": 27,
      "firstName": "Sharl",
      "lastName": "Woolfitt",
      "dob": "2018-11-12",
      "crn": "846656484-5"
    },
    {
      "id": 28,
      "firstName": "Lorne",
      "lastName": "Alesi",
      "dob": "2020-05-27",
      "crn": "631588979-4"
    },
    {
      "id": 29,
      "firstName": "Teddy",
      "lastName": "Vears",
      "dob": "2019-10-18",
      "crn": "368362368-3"
    },
    {
      "id": 30,
      "firstName": "Aline",
      "lastName": "Urpeth",
      "dob": "2019-06-11",
      "crn": "804511422-3"
    },
    {
      "id": 31,
      "firstName": "Dyana",
      "lastName": "Moysey",
      "dob": "2018-07-13",
      "crn": "589806865-1"
    },
    {
      "id": 32,
      "firstName": "Bobbi",
      "lastName": "Eliot",
      "dob": "2021-01-08",
      "crn": "393231162-0"
    },
    {
      "id": 33,
      "firstName": "Joane",
      "lastName": "Bilbrook",
      "dob": "2019-05-18",
      "crn": "748179413-8"
    },
    {
      "id": 34,
      "firstName": "Alwyn",
      "lastName": "Durrington",
      "dob": "2019-11-01",
      "crn": "011162051-1"
    },
    {
      "id": 35,
      "firstName": "Germana",
      "lastName": "Joss",
      "dob": "2020-09-25",
      "crn": "863202349-7"
    },
    {
      "id": 36,
      "firstName": "Jamesy",
      "lastName": "Massimo",
      "dob": "2019-09-13",
      "crn": "642855217-5"
    },
    {
      "id": 37,
      "firstName": "Joshia",
      "lastName": "Meldon",
      "dob": "2018-06-11",
      "crn": "715494664-4"
    },
    {
      "id": 38,
      "firstName": "Barbey",
      "lastName": "Clutterbuck",
      "dob": "2019-08-18",
      "crn": "215032453-9"
    },
    {
      "id": 39,
      "firstName": "Erinna",
      "lastName": "Di Dello",
      "dob": "2020-09-08",
      "crn": "141516882-2"
    },
    {
      "id": 40,
      "firstName": "Chevy",
      "lastName": "Baddow",
      "dob": "2018-07-18",
      "crn": "766729242-6"
    },
    {
      "id": 41,
      "firstName": "Wilmar",
      "lastName": "Dwerryhouse",
      "dob": "2019-04-03",
      "crn": "414477860-6"
    },
    {
      "id": 42,
      "firstName": "Mic",
      "lastName": "Domaschke",
      "dob": "2018-11-28",
      "crn": "324617611-6"
    },
    {
      "id": 43,
      "firstName": "Ashien",
      "lastName": "Vondrak",
      "dob": "2021-03-16",
      "crn": "802122517-3"
    },
    {
      "id": 44,
      "firstName": "Laure",
      "lastName": "Proudlove",
      "dob": "2020-04-08",
      "crn": "757579684-3"
    },
    {
      "id": 45,
      "firstName": "Goldy",
      "lastName": "Peaurt",
      "dob": "2018-09-05",
      "crn": "842482725-2"
    },
    {
      "id": 46,
      "firstName": "Vin",
      "lastName": "Temprell",
      "dob": "2019-12-29",
      "crn": "676474058-5"
    },
    {
      "id": 47,
      "firstName": "Reinaldo",
      "lastName": "Richmond",
      "dob": "2019-04-09",
      "crn": "136747870-7"
    },
    {
      "id": 48,
      "firstName": "Yul",
      "lastName": "Balmforth",
      "dob": "2020-02-29",
      "crn": "022813108-1"
    },
    {
      "id": 49,
      "firstName": "Conrad",
      "lastName": "Benka",
      "dob": "2020-05-13",
      "crn": "655975644-0"
    },
    {
      "id": 50,
      "firstName": "Esra",
      "lastName": "Nell",
      "dob": "2019-08-17",
      "crn": "188034239-1"
    },
    {
      "id": 51,
      "firstName": "Caroljean",
      "lastName": "Hatwell",
      "dob": "2020-10-19",
      "crn": "692203244-6"
    },
    {
      "id": 52,
      "firstName": "Debi",
      "lastName": "D'eath",
      "dob": "2020-10-24",
      "crn": "780066733-2"
    },
    {
      "id": 53,
      "firstName": "Nicky",
      "lastName": "Rider",
      "dob": "2019-01-16",
      "crn": "208499101-3"
    },
    {
      "id": 54,
      "firstName": "Sabra",
      "lastName": "Jefferson",
      "dob": "2019-08-23",
      "crn": "929552061-0"
    },
    {
      "id": 55,
      "firstName": "Ilse",
      "lastName": "Ancketill",
      "dob": "2020-02-11",
      "crn": "673902601-7"
    },
    {
      "id": 56,
      "firstName": "Margarette",
      "lastName": "Kinnon",
      "dob": "2020-08-03",
      "crn": "808919920-8"
    },
    {
      "id": 57,
      "firstName": "Trixi",
      "lastName": "Agnew",
      "dob": "2019-09-13",
      "crn": "754932655-X"
    },
    {
      "id": 58,
      "firstName": "Blancha",
      "lastName": "Poel",
      "dob": "2020-06-28",
      "crn": "712681793-2"
    },
    {
      "id": 59,
      "firstName": "Dru",
      "lastName": "Shimmans",
      "dob": "2020-08-03",
      "crn": "678777401-X"
    },
    {
      "id": 60,
      "firstName": "Genovera",
      "lastName": "Letessier",
      "dob": "2018-09-11",
      "crn": "413899745-8"
    },
    {
      "id": 61,
      "firstName": "Blinny",
      "lastName": "Lambertazzi",
      "dob": "2019-05-17",
      "crn": "038894300-9"
    },
    {
      "id": 62,
      "firstName": "Robina",
      "lastName": "Geggie",
      "dob": "2019-10-13",
      "crn": "258990354-5"
    },
    {
      "id": 63,
      "firstName": "Mirabelle",
      "lastName": "Castard",
      "dob": "2019-03-12",
      "crn": "863784743-9"
    },
    {
      "id": 64,
      "firstName": "Lesli",
      "lastName": "Solomon",
      "dob": "2021-01-04",
      "crn": "370614309-7"
    },
    {
      "id": 65,
      "firstName": "Timothy",
      "lastName": "Stanion",
      "dob": "2020-04-17",
      "crn": "003885133-4"
    },
    {
      "id": 66,
      "firstName": "Natalee",
      "lastName": "Dingwall",
      "dob": "2019-08-07",
      "crn": "686357060-2"
    },
    {
      "id": 67,
      "firstName": "Audrey",
      "lastName": "Synnott",
      "dob": "2018-12-09",
      "crn": "644589637-5"
    },
    {
      "id": 68,
      "firstName": "Aggie",
      "lastName": "Haquin",
      "dob": "2019-01-02",
      "crn": "466297774-6"
    },
    {
      "id": 69,
      "firstName": "Lesley",
      "lastName": "Doge",
      "dob": "2019-05-25",
      "crn": "229954387-2"
    },
    {
      "id": 70,
      "firstName": "Jesus",
      "lastName": "Doumic",
      "dob": "2019-10-18",
      "crn": "869302064-1"
    },
    {
      "id": 71,
      "firstName": "Jeana",
      "lastName": "Bastock",
      "dob": "2019-08-15",
      "crn": "006357056-4"
    },
    {
      "id": 72,
      "firstName": "Alfy",
      "lastName": "Balderson",
      "dob": "2020-10-28",
      "crn": "589527919-8"
    },
    {
      "id": 73,
      "firstName": "Nevil",
      "lastName": "Digweed",
      "dob": "2020-01-13",
      "crn": "086986052-6"
    },
    {
      "id": 74,
      "firstName": "Marleen",
      "lastName": "Swanborrow",
      "dob": "2020-12-28",
      "crn": "053179622-1"
    },
    {
      "id": 75,
      "firstName": "Bianka",
      "lastName": "Sinderson",
      "dob": "2021-02-19",
      "crn": "223865114-4"
    },
    {
      "id": 76,
      "firstName": "La verne",
      "lastName": "Sedgwick",
      "dob": "2020-07-31",
      "crn": "590849813-0"
    },
    {
      "id": 77,
      "firstName": "Ibbie",
      "lastName": "Sea",
      "dob": "2021-04-09",
      "crn": "355605231-8"
    },
    {
      "id": 78,
      "firstName": "Flori",
      "lastName": "Oxtoby",
      "dob": "2019-12-19",
      "crn": "629325026-5"
    },
    {
      "id": 79,
      "firstName": "Goldia",
      "lastName": "Oven",
      "dob": "2019-11-22",
      "crn": "782670453-7"
    },
    {
      "id": 80,
      "firstName": "Marthe",
      "lastName": "Lessmare",
      "dob": "2020-12-31",
      "crn": "431117840-9"
    },
    {
      "id": 81,
      "firstName": "Mela",
      "lastName": "Christescu",
      "dob": "2019-09-14",
      "crn": "840688941-1"
    },
    {
      "id": 82,
      "firstName": "Ramona",
      "lastName": "Levicount",
      "dob": "2018-11-15",
      "crn": "311036992-3"
    },
    {
      "id": 83,
      "firstName": "Griswold",
      "lastName": "Cottom",
      "dob": "2018-08-09",
      "crn": "621271840-7"
    },
    {
      "id": 84,
      "firstName": "Diann",
      "lastName": "Piggford",
      "dob": "2020-01-06",
      "crn": "356283157-9"
    },
    {
      "id": 85,
      "firstName": "Tanner",
      "lastName": "Farrar",
      "dob": "2018-08-09",
      "crn": "867764181-5"
    },
    {
      "id": 86,
      "firstName": "Lemmy",
      "lastName": "Wrighton",
      "dob": "2018-08-31",
      "crn": "872328304-1"
    },
    {
      "id": 87,
      "firstName": "Derk",
      "lastName": "Moger",
      "dob": "2020-01-01",
      "crn": "702409257-2"
    },
    {
      "id": 88,
      "firstName": "Nicole",
      "lastName": "Celez",
      "dob": "2019-02-17",
      "crn": "146266363-X"
    },
    {
      "id": 89,
      "firstName": "Zilvia",
      "lastName": "Mongenot",
      "dob": "2019-09-22",
      "crn": "924056080-7"
    },
    {
      "id": 90,
      "firstName": "Letti",
      "lastName": "Tomenson",
      "dob": "2021-02-04",
      "crn": "716877506-5"
    },
    {
      "id": 91,
      "firstName": "Sherilyn",
      "lastName": "Clevely",
      "dob": "2019-03-26",
      "crn": "896420858-7"
    },
    {
      "id": 92,
      "firstName": "Tierney",
      "lastName": "Stainburn",
      "dob": "2018-12-05",
      "crn": "496247352-2"
    },
    {
      "id": 93,
      "firstName": "Gray",
      "lastName": "Heathfield",
      "dob": "2018-09-24",
      "crn": "907031378-2"
    },
    {
      "id": 94,
      "firstName": "Hieronymus",
      "lastName": "Murrigan",
      "dob": "2020-06-23",
      "crn": "671084953-8"
    },
    {
      "id": 95,
      "firstName": "Bale",
      "lastName": "Camp",
      "dob": "2018-11-14",
      "crn": "897065352-X"
    },
    {
      "id": 96,
      "firstName": "Kenny",
      "lastName": "Whitebrook",
      "dob": "2020-02-11",
      "crn": "710557257-4"
    },
    {
      "id": 97,
      "firstName": "Leicester",
      "lastName": "Casel",
      "dob": "2019-05-28",
      "crn": "167166771-9"
    },
    {
      "id": 98,
      "firstName": "Broddie",
      "lastName": "Fullicks",
      "dob": "2020-08-01",
      "crn": "019989288-1"
    },
    {
      "id": 99,
      "firstName": "Mel",
      "lastName": "Sherme",
      "dob": "2020-06-27",
      "crn": "224941812-8"
    },
    {
      "id": 100,
      "firstName": "Wanids",
      "lastName": "Garcia",
      "dob": "2021-02-15",
      "crn": "745002569-8"
    },
    {
      "id": 101,
      "firstName": "Larissa",
      "lastName": "Wilson"
    },
    {
      "id": 102,
      "firstName": "Junior",
      "lastName": "Bigoo"
    }
  ],
  "enquiries": [
    {
      "id": 1,
      "contactId": 1,
      "centreId": 1,
      "children": [
        1,
        2
      ],
      "enquiryDate": "2021-03-01",
      "preferredStartDate": "2021-03-01"
    },
    {
      "id": 2,
      "contactId": 1,
      "centreId": 2,
      "children": [
        1,
        2
      ],
      "enquiryDate": "2021-03-01",
      "preferredStartDate": "2021-03-01"
    },
    {
      "id": 3,
      "centreId": 2,
      "children": [
        101
      ],
      "preferredStartDate": "Larissa",
      "contactId": 103,
      "enquiryDate": "2021-04-11"
    },
    {
      "id": 4,
      "centreId": 2,
      "children": [
        102
      ],
      "preferredStartDate": "Junior",
      "contactId": 104,
      "enquiryDate": "2021-04-11"
    }
  ],
  "contacts": [
    {
      "id": 1,
      "firstName": "Lauren",
      "lastName": "Eubank",
      "dob": "2005-04-10",
      "crn": "908350127-2",
      "email": "leubank0@google.co.uk",
      "phone": "8594508746",
      "address": "67 Esch Road",
      "suburb": "",
      "state": "",
      "postcode": "",
      "relatedContactId": [],
      "children": []
    },
    {
      "id": 2,
      "firstName": "Jodi",
      "lastName": "Lorentz",
      "dob": "2005-01-06",
      "crn": "191733997-6",
      "email": "jlorentz1@sogou.com",
      "phone": "3501838337",
      "address": "1 Toban Trail",
      "suburb": "",
      "state": "",
      "postcode": "",
      "relatedContactId": [],
      "children": []
    },
    {
      "id": 3,
      "firstName": "Jorge",
      "lastName": "Cornau",
      "dob": "1990-11-14",
      "crn": "511280299-5",
      "email": "jcornau2@networkadvertising.org",
      "phone": "9319276894",
      "address": "0 Oxford Alley",
      "suburb": "",
      "state": "",
      "postcode": "",
      "relatedContactId": [],
      "children": []
    },
    {
      "id": 4,
      "firstName": "Mikael",
      "lastName": "Primo",
      "dob": "1996-06-30",
      "crn": "294470968-2",
      "email": "mprimo3@scientificamerican.com",
      "phone": "9354774625",
      "address": "78 Jay Point",
      "suburb": "",
      "state": "",
      "postcode": "",
      "relatedContactId": [],
      "children": []
    },
    {
      "id": 5,
      "firstName": "Janeta",
      "lastName": "Skillitt",
      "dob": "1986-09-07",
      "crn": "840349325-8",
      "email": "jskillitt4@ft.com",
      "phone": "3054952595",
      "address": "74 Saint Paul Drive",
      "suburb": "",
      "state": "",
      "postcode": "",
      "relatedContactId": [],
      "children": []
    },
    {
      "id": 6,
      "firstName": "Shannen",
      "lastName": "Sandell",
      "dob": "1998-04-30",
      "crn": "322130254-1",
      "email": "ssandell5@cyberchimps.com",
      "phone": "6137456593",
      "address": "94416 Bluestem Lane",
      "suburb": "",
      "state": "",
      "postcode": "",
      "relatedContactId": [],
      "children": []
    },
    {
      "id": 7,
      "firstName": "Gnni",
      "lastName": "Burnage",
      "dob": "2002-10-24",
      "crn": "009009287-2",
      "email": "gburnage6@buzzfeed.com",
      "phone": "4669384532",
      "address": "26 Prairieview Center",
      "suburb": "",
      "state": "",
      "postcode": "",
      "relatedContactId": [],
      "children": []
    },
    {
      "id": 8,
      "firstName": "Marietta",
      "lastName": "Brocking",
      "dob": "1997-12-02",
      "crn": "497959953-2",
      "email": "mbrocking7@desdev.cn",
      "phone": "1541103696",
      "address": "01 Darwin Avenue",
      "suburb": "",
      "state": "",
      "postcode": "",
      "relatedContactId": [],
      "children": []
    },
    {
      "id": 9,
      "firstName": "Yvor",
      "lastName": "Drew-Clifton",
      "dob": "1980-11-29",
      "crn": "195160302-8",
      "email": "ydrewclifton8@drupal.org",
      "phone": "5288257778",
      "address": "553 Holmberg Avenue",
      "suburb": "",
      "state": "",
      "postcode": "",
      "relatedContactId": [],
      "children": []
    },
    {
      "id": 10,
      "firstName": "Ciro",
      "lastName": "Porson",
      "dob": "2004-07-18",
      "crn": "441985380-8",
      "email": "cporson9@sina.com.cn",
      "phone": "4722390001",
      "address": "9304 Farragut Crossing",
      "suburb": "",
      "state": "",
      "postcode": "",
      "relatedContactId": [],
      "children": []
    },
    {
      "id": 11,
      "firstName": "Janean",
      "lastName": "Betz",
      "dob": "2000-12-25",
      "crn": "441269222-1",
      "email": "jbetza@google.com.au",
      "phone": "5954254249",
      "address": "60749 Maywood Way",
      "suburb": "",
      "state": "",
      "postcode": "",
      "relatedContactId": [],
      "children": []
    },
    {
      "id": 12,
      "firstName": "Shannon",
      "lastName": "Semor",
      "dob": "1987-06-10",
      "crn": "661627997-9",
      "email": "ssemorb@earthlink.net",
      "phone": "5378744569",
      "address": "9226 Raven Road",
      "suburb": "",
      "state": "",
      "postcode": "",
      "relatedContactId": [],
      "children": []
    },
    {
      "id": 13,
      "firstName": "Ainsley",
      "lastName": "Beames",
      "dob": "1981-06-29",
      "crn": "502832454-9",
      "email": "abeamesc@bravesites.com",
      "phone": "8243259065",
      "address": "7 Truax Place",
      "suburb": "",
      "state": "",
      "postcode": "",
      "relatedContactId": [],
      "children": []
    },
    {
      "id": 14,
      "firstName": "Giralda",
      "lastName": "Blackman",
      "dob": "2002-04-12",
      "crn": "051228672-8",
      "email": "gblackmand@tinyurl.com",
      "phone": "6421203182",
      "address": "14552 Bayside Pass",
      "suburb": "",
      "state": "",
      "postcode": "",
      "relatedContactId": [],
      "children": []
    },
    {
      "id": 15,
      "firstName": "Bat",
      "lastName": "Ansell",
      "dob": "1990-05-21",
      "crn": "278714106-4",
      "email": "banselle@tripadvisor.com",
      "phone": "3316418610",
      "address": "659 Doe Crossing Crossing",
      "suburb": "",
      "state": "",
      "postcode": "",
      "relatedContactId": [],
      "children": []
    },
    {
      "id": 16,
      "firstName": "Sacha",
      "lastName": "Carde",
      "dob": "1992-12-16",
      "crn": "445362164-7",
      "email": "scardef@craigslist.org",
      "phone": "4069950452",
      "address": "437 Steensland Drive",
      "suburb": "",
      "state": "",
      "postcode": "",
      "relatedContactId": [],
      "children": []
    },
    {
      "id": 17,
      "firstName": "Bettye",
      "lastName": "Northey",
      "dob": "1992-12-26",
      "crn": "556791311-7",
      "email": "bnortheyg@upenn.edu",
      "phone": "4249627442",
      "address": "4 Pennsylvania Crossing",
      "suburb": "",
      "state": "",
      "postcode": "",
      "relatedContactId": [],
      "children": []
    },
    {
      "id": 18,
      "firstName": "Corilla",
      "lastName": "Leeuwerink",
      "dob": "1994-01-09",
      "crn": "490961919-4",
      "email": "cleeuwerinkh@jugem.jp",
      "phone": "8164889106",
      "address": "9916 Stuart Lane",
      "suburb": "",
      "state": "",
      "postcode": "",
      "relatedContactId": [],
      "children": []
    },
    {
      "id": 19,
      "firstName": "Rozanna",
      "lastName": "Whitcher",
      "dob": "1992-12-18",
      "crn": "624065200-8",
      "email": "rwhitcheri@is.gd",
      "phone": "3603009670",
      "address": "9 Del Mar Point",
      "suburb": "",
      "state": "",
      "postcode": "",
      "relatedContactId": [],
      "children": []
    },
    {
      "id": 20,
      "firstName": "Roberta",
      "lastName": "Remington",
      "dob": "1982-05-05",
      "crn": "660879879-2",
      "email": "rremingtonj@comcast.net",
      "phone": "2032137116",
      "address": "69467 Del Mar Circle",
      "suburb": "",
      "state": "",
      "postcode": "",
      "relatedContactId": [],
      "children": []
    },
    {
      "id": 21,
      "firstName": "Eli",
      "lastName": "Josephov",
      "dob": "1990-04-29",
      "crn": "425690642-8",
      "email": "ejosephovk@google.fr",
      "phone": "1111208495",
      "address": "124 Scofield Drive",
      "suburb": "",
      "state": "",
      "postcode": "",
      "relatedContactId": [],
      "children": []
    },
    {
      "id": 22,
      "firstName": "Lorin",
      "lastName": "Riedel",
      "dob": "2001-07-20",
      "crn": "406890031-0",
      "email": "lriedell@slashdot.org",
      "phone": "5362330594",
      "address": "77 Sloan Parkway",
      "suburb": "",
      "state": "",
      "postcode": "",
      "relatedContactId": [],
      "children": []
    },
    {
      "id": 23,
      "firstName": "Arlina",
      "lastName": "Brash",
      "dob": "1993-12-13",
      "crn": "604816739-3",
      "email": "abrashm@biglobe.ne.jp",
      "phone": "7988915226",
      "address": "6 Sherman Center",
      "suburb": "",
      "state": "",
      "postcode": "",
      "relatedContactId": [],
      "children": []
    },
    {
      "id": 24,
      "firstName": "Cindra",
      "lastName": "Picard",
      "dob": "1985-12-04",
      "crn": "331128480-1",
      "email": "cpicardn@harvard.edu",
      "phone": "1505876920",
      "address": "2229 Rieder Court",
      "suburb": "",
      "state": "",
      "postcode": "",
      "relatedContactId": [],
      "children": []
    },
    {
      "id": 25,
      "firstName": "Zora",
      "lastName": "Verrechia",
      "dob": "1983-12-11",
      "crn": "894015002-3",
      "email": "zverrechiao@addthis.com",
      "phone": "7222508143",
      "address": "4 Randy Circle",
      "suburb": "",
      "state": "",
      "postcode": "",
      "relatedContactId": [],
      "children": []
    },
    {
      "id": 26,
      "firstName": "Phillida",
      "lastName": "Blake",
      "dob": "1998-03-31",
      "crn": "091682730-5",
      "email": "pblakep@amazon.co.jp",
      "phone": "5656209558",
      "address": "8 Meadow Vale Terrace",
      "suburb": "",
      "state": "",
      "postcode": "",
      "relatedContactId": [],
      "children": []
    },
    {
      "id": 27,
      "firstName": "Jessi",
      "lastName": "Mazzey",
      "dob": "1989-09-01",
      "crn": "321864876-9",
      "email": "jmazzeyq@intel.com",
      "phone": "4169775066",
      "address": "3108 Anzinger Terrace",
      "suburb": "",
      "state": "",
      "postcode": "",
      "relatedContactId": [],
      "children": []
    },
    {
      "id": 28,
      "firstName": "Leonore",
      "lastName": "Pargetter",
      "dob": "1983-05-23",
      "crn": "232984616-9",
      "email": "lpargetterr@discuz.net",
      "phone": "2951484127",
      "address": "4 Sauthoff Trail",
      "suburb": "",
      "state": "",
      "postcode": "",
      "relatedContactId": [],
      "children": []
    },
    {
      "id": 29,
      "firstName": "Hugh",
      "lastName": "Malthouse",
      "dob": "1999-02-26",
      "crn": "097782437-3",
      "email": "hmalthouses@time.com",
      "phone": "7215143063",
      "address": "36308 Oak Park",
      "suburb": "",
      "state": "",
      "postcode": "",
      "relatedContactId": [],
      "children": []
    },
    {
      "id": 30,
      "firstName": "Janifer",
      "lastName": "Braunlein",
      "dob": "1999-04-15",
      "crn": "188754429-1",
      "email": "jbraunleint@canalblog.com",
      "phone": "9828121882",
      "address": "7616 Meadow Vale Alley",
      "suburb": "",
      "state": "",
      "postcode": "",
      "relatedContactId": [],
      "children": []
    },
    {
      "id": 31,
      "firstName": "Mureil",
      "lastName": "Lempertz",
      "dob": "2000-05-13",
      "crn": "169418747-0",
      "email": "mlempertzu@free.fr",
      "phone": "1096475034",
      "address": "18308 Carey Road",
      "suburb": "",
      "state": "",
      "postcode": "",
      "relatedContactId": [],
      "children": []
    },
    {
      "id": 32,
      "firstName": "Brandais",
      "lastName": "Starmer",
      "dob": "1995-03-09",
      "crn": "325762527-8",
      "email": "bstarmerv@squidoo.com",
      "phone": "6561302348",
      "address": "56939 Lotheville Park",
      "suburb": "",
      "state": "",
      "postcode": "",
      "relatedContactId": [],
      "children": []
    },
    {
      "id": 33,
      "firstName": "Farris",
      "lastName": "Teresi",
      "dob": "1997-03-25",
      "crn": "068315699-3",
      "email": "fteresiw@slashdot.org",
      "phone": "1693180254",
      "address": "1512 Jay Junction",
      "suburb": "",
      "state": "",
      "postcode": "",
      "relatedContactId": [],
      "children": []
    },
    {
      "id": 34,
      "firstName": "Isiahi",
      "lastName": "Campsall",
      "dob": "2004-12-10",
      "crn": "883230276-4",
      "email": "icampsallx@ow.ly",
      "phone": "4584694674",
      "address": "2886 Green Ridge Place",
      "suburb": "",
      "state": "",
      "postcode": "",
      "relatedContactId": [],
      "children": []
    },
    {
      "id": 35,
      "firstName": "Lucretia",
      "lastName": "Apedaile",
      "dob": "1984-08-07",
      "crn": "358288698-0",
      "email": "lapedailey@mtv.com",
      "phone": "9467938106",
      "address": "99580 Porter Court",
      "suburb": "",
      "state": "",
      "postcode": "",
      "relatedContactId": [],
      "children": []
    },
    {
      "id": 36,
      "firstName": "Angy",
      "lastName": "Lanchbury",
      "dob": "1994-07-22",
      "crn": "395691633-6",
      "email": "alanchburyz@npr.org",
      "phone": "7578995416",
      "address": "806 Bay Lane",
      "suburb": "",
      "state": "",
      "postcode": "",
      "relatedContactId": [],
      "children": []
    },
    {
      "id": 37,
      "firstName": "Philippine",
      "lastName": "Mulvany",
      "dob": "1993-04-08",
      "crn": "149556896-2",
      "email": "pmulvany10@amazon.de",
      "phone": "2097901773",
      "address": "181 Spenser Drive",
      "suburb": "",
      "state": "",
      "postcode": "",
      "relatedContactId": [],
      "children": []
    },
    {
      "id": 38,
      "firstName": "Thorny",
      "lastName": "Pinchbeck",
      "dob": "2002-04-10",
      "crn": "406954965-X",
      "email": "tpinchbeck11@live.com",
      "phone": "2729037781",
      "address": "41597 Bartelt Crossing",
      "suburb": "",
      "state": "",
      "postcode": "",
      "relatedContactId": [],
      "children": []
    },
    {
      "id": 39,
      "firstName": "Bradan",
      "lastName": "Earlam",
      "dob": "1987-09-30",
      "crn": "794177164X",
      "email": "bearlam12@twitpic.com",
      "phone": "8536494312",
      "address": "3 Copson St, Clontarf QLD 4019, Australia",
      "suburb": "Copson St",
      "state": "Moreton Bay Region",
      "postcode": "AU",
      "relatedContactId": [],
      "children": [],
      "addressLat": -27.2529067,
      "addresssLng": 153.0782562
    },
    {
      "id": 40,
      "firstName": "Pierette",
      "lastName": "Madeley",
      "dob": "1996-06-25",
      "crn": "701423654-7",
      "email": "pmadeley13@cisco.com",
      "phone": "4621072046",
      "address": "27227 Crowley Plaza",
      "suburb": "",
      "state": "",
      "postcode": "",
      "relatedContactId": [],
      "children": []
    },
    {
      "id": 41,
      "firstName": "Lewie",
      "lastName": "Lander",
      "dob": "1996-01-01",
      "crn": "718468595-4",
      "email": "llander14@over-blog.com",
      "phone": "6767824608",
      "address": "8722 Barby Center",
      "suburb": "",
      "state": "",
      "postcode": "",
      "relatedContactId": [],
      "children": []
    },
    {
      "id": 42,
      "firstName": "Harlan",
      "lastName": "Noyes",
      "dob": "2002-11-30",
      "crn": "909743232-4",
      "email": "hnoyes15@epa.gov",
      "phone": "9123474413",
      "address": "9 Dakota Crossing",
      "suburb": "",
      "state": "",
      "postcode": "",
      "relatedContactId": [],
      "children": []
    },
    {
      "id": 43,
      "firstName": "Brit",
      "lastName": "Lashley",
      "dob": "2002-09-06",
      "crn": "628848407-5",
      "email": "blashley16@taobao.com",
      "phone": "9958464404",
      "address": "669 Lakewood Parkway",
      "suburb": "",
      "state": "",
      "postcode": "",
      "relatedContactId": [],
      "children": []
    },
    {
      "id": 44,
      "firstName": "Jada",
      "lastName": "Teresa",
      "dob": "2002-09-03",
      "crn": "714048050-8",
      "email": "jteresa17@nationalgeographic.com",
      "phone": "1786256394",
      "address": "02795 Upham Circle",
      "suburb": "",
      "state": "",
      "postcode": "",
      "relatedContactId": [],
      "children": []
    },
    {
      "id": 45,
      "firstName": "Jojo",
      "lastName": "Weond",
      "dob": "1986-04-27",
      "crn": "196745440-X",
      "email": "jweond18@instagram.com",
      "phone": "9576521117",
      "address": "33417 Kim Way",
      "suburb": "",
      "state": "",
      "postcode": "",
      "relatedContactId": [],
      "children": []
    },
    {
      "id": 46,
      "firstName": "Orlando",
      "lastName": "Van Halle",
      "dob": "1991-12-09",
      "crn": "998983155-6",
      "email": "ovanhalle19@mac.com",
      "phone": "9789077554",
      "address": "821 Gale Trail",
      "suburb": "",
      "state": "",
      "postcode": "",
      "relatedContactId": [],
      "children": []
    },
    {
      "id": 47,
      "firstName": "Lisabeth",
      "lastName": "Ollivier",
      "dob": "1983-02-25",
      "crn": "219970757-1",
      "email": "lollivier1a@phpbb.com",
      "phone": "3626918193",
      "address": "3 Copson St, Clontarf QLD 4019, Australia",
      "suburb": "",
      "state": "",
      "postcode": "",
      "relatedContactId": [],
      "children": [],
      "addressLat": -27.2529067,
      "addresssLng": 153.0782562
    },
    {
      "id": 48,
      "firstName": "Skippy",
      "lastName": "Egglestone",
      "dob": "1987-11-28",
      "crn": "492646430-6",
      "email": "segglestone1b@umich.edu",
      "phone": "4534413402",
      "address": "0838 Dahle Center",
      "suburb": "",
      "state": "",
      "postcode": "",
      "relatedContactId": [],
      "children": []
    },
    {
      "id": 49,
      "firstName": "Zenia",
      "lastName": "Nell",
      "dob": "1986-04-21",
      "crn": "880591340-5",
      "email": "znell1c@cocolog-nifty.com",
      "phone": "8831231245",
      "address": "17 Reindahl Center",
      "suburb": "",
      "state": "",
      "postcode": "",
      "relatedContactId": [],
      "children": []
    },
    {
      "id": 50,
      "firstName": "Curtis",
      "lastName": "Sirmond",
      "dob": "1985-07-23",
      "crn": "850108368-2",
      "email": "csirmond1d@examiner.com",
      "phone": "6826595283",
      "address": "67117 Randy Center",
      "suburb": "",
      "state": "",
      "postcode": "",
      "relatedContactId": [],
      "children": []
    },
    {
      "id": 51,
      "firstName": "Roosevelt",
      "lastName": "Cheese",
      "dob": "1986-01-21",
      "crn": "986085864-0",
      "email": "rcheese1e@ucoz.ru",
      "phone": "6793235086",
      "address": "30 Dexter Junction",
      "suburb": "",
      "state": "",
      "postcode": "",
      "relatedContactId": [],
      "children": []
    },
    {
      "id": 52,
      "firstName": "Janella",
      "lastName": "Avramchik",
      "dob": "1984-06-21",
      "crn": "844706985-0",
      "email": "javramchik1f@huffingtonpost.com",
      "phone": "9598210139",
      "address": "95 Buhler Park",
      "suburb": "",
      "state": "",
      "postcode": "",
      "relatedContactId": [],
      "children": []
    },
    {
      "id": 53,
      "firstName": "Anallise",
      "lastName": "Strauss",
      "dob": "1999-11-24",
      "crn": "363557402-3",
      "email": "astrauss1g@aol.com",
      "phone": "1579865019",
      "address": "90024 Elmside Hill",
      "suburb": "",
      "state": "",
      "postcode": "",
      "relatedContactId": [],
      "children": []
    },
    {
      "id": 54,
      "firstName": "Adelbert",
      "lastName": "Kerry",
      "dob": "1986-11-27",
      "crn": "925616465-5",
      "email": "akerry1h@1688.com",
      "phone": "3478564280",
      "address": "247 Jenifer Road",
      "suburb": "",
      "state": "",
      "postcode": "",
      "relatedContactId": [],
      "children": []
    },
    {
      "id": 55,
      "firstName": "Jenni",
      "lastName": "Eckart",
      "dob": "1992-11-04",
      "crn": "245387763-1",
      "email": "jeckart1i@simplemachines.org",
      "phone": "4135279133",
      "address": "110 Old Gate Drive",
      "suburb": "",
      "state": "",
      "postcode": "",
      "relatedContactId": [],
      "children": []
    },
    {
      "id": 56,
      "firstName": "Vi",
      "lastName": "McHarry",
      "dob": "1991-09-30",
      "crn": "323205642-3",
      "email": "vmcharry1j@pen.io",
      "phone": "1768075877",
      "address": "3 Sunfield Trail",
      "suburb": "",
      "state": "",
      "postcode": "",
      "relatedContactId": [],
      "children": []
    },
    {
      "id": 57,
      "firstName": "Vinnie",
      "lastName": "Milksop",
      "dob": "1994-10-17",
      "crn": "225793955-7",
      "email": "vmilksop1k@msu.edu",
      "phone": "9529634009",
      "address": "91 Longview Lane",
      "suburb": "",
      "state": "",
      "postcode": "",
      "relatedContactId": [],
      "children": []
    },
    {
      "id": 58,
      "firstName": "Harcourt",
      "lastName": "McAllester",
      "dob": "1997-10-16",
      "crn": "460148508-8",
      "email": "hmcallester1l@sitemeter.com",
      "phone": "8541282291",
      "address": "06941 Helena Trail",
      "suburb": "",
      "state": "",
      "postcode": "",
      "relatedContactId": [],
      "children": []
    },
    {
      "id": 59,
      "firstName": "Sophia",
      "lastName": "Andraud",
      "dob": "1987-09-03",
      "crn": "756619039-3",
      "email": "sandraud1m@irs.gov",
      "phone": "3256227992",
      "address": "074 Anderson Circle",
      "suburb": "",
      "state": "",
      "postcode": "",
      "relatedContactId": [],
      "children": []
    },
    {
      "id": 60,
      "firstName": "Shaun",
      "lastName": "Blind",
      "dob": "1987-06-22",
      "crn": "999439316-2",
      "email": "sblind1n@fda.gov",
      "phone": "3148556533",
      "address": "49868 Lunder Pass",
      "suburb": "",
      "state": "",
      "postcode": "",
      "relatedContactId": [],
      "children": []
    },
    {
      "id": 61,
      "firstName": "Sheena",
      "lastName": "Clunan",
      "dob": "1994-04-07",
      "crn": "156223683-0",
      "email": "sclunan1o@weebly.com",
      "phone": "1438447056",
      "address": "6717 Alpine Plaza",
      "suburb": "",
      "state": "",
      "postcode": "",
      "relatedContactId": [],
      "children": []
    },
    {
      "id": 62,
      "firstName": "Tomi",
      "lastName": "Hayman",
      "dob": "1983-01-12",
      "crn": "385468271-9",
      "email": "thayman1p@symantec.com",
      "phone": "1422052076",
      "address": "2254 Schlimgen Plaza",
      "suburb": "",
      "state": "",
      "postcode": "",
      "relatedContactId": [],
      "children": []
    },
    {
      "id": 63,
      "firstName": "Frederique",
      "lastName": "Daines",
      "dob": "1984-09-10",
      "crn": "027551577-X",
      "email": "fdaines1q@ihg.com",
      "phone": "5588396058",
      "address": "49 Gateway St, Wynnum West QLD 4178, Australia",
      "suburb": "",
      "state": "",
      "postcode": "",
      "relatedContactId": [],
      "children": [],
      "addressLat": -27.4569319,
      "addresssLng": 153.1612959
    },
    {
      "id": 64,
      "firstName": "Ray",
      "lastName": "Alentyev",
      "dob": "1983-04-21",
      "crn": "352797523-3",
      "email": "ralentyev1r@parallels.com",
      "phone": "9886590449",
      "address": "4 Summer Ridge Crossing",
      "suburb": "",
      "state": "",
      "postcode": "",
      "relatedContactId": [],
      "children": []
    },
    {
      "id": 65,
      "firstName": "Arliene",
      "lastName": "Coughlin",
      "dob": "2001-06-20",
      "crn": "678262836-8",
      "email": "acoughlin1s@cnbc.com",
      "phone": "5141217899",
      "address": "960 Texas Lane",
      "suburb": "",
      "state": "",
      "postcode": "",
      "relatedContactId": [],
      "children": []
    },
    {
      "id": 66,
      "firstName": "Cristionna",
      "lastName": "Allsupp",
      "dob": "1987-10-31",
      "crn": "476614905-X",
      "email": "callsupp1t@ftc.gov",
      "phone": "3916392541",
      "address": "19 Talisman Junction",
      "suburb": "",
      "state": "",
      "postcode": "",
      "relatedContactId": [],
      "children": []
    },
    {
      "id": 67,
      "firstName": "Bernadette",
      "lastName": "Ricca",
      "dob": "1994-01-21",
      "crn": "014778745-9",
      "email": "bricca1u@pcworld.com",
      "phone": "9318409587",
      "address": "2461 Spaight Circle",
      "suburb": "",
      "state": "",
      "postcode": "",
      "relatedContactId": [],
      "children": []
    },
    {
      "id": 68,
      "firstName": "Paola",
      "lastName": "Pelerin",
      "dob": "1981-12-15",
      "crn": "044622804-4",
      "email": "ppelerin1v@technorati.com",
      "phone": "8913060076",
      "address": "3 Oak Parkway",
      "suburb": "",
      "state": "",
      "postcode": "",
      "relatedContactId": [],
      "children": []
    },
    {
      "id": 69,
      "firstName": "Elwyn",
      "lastName": "Godfree",
      "dob": "1996-09-14",
      "crn": "717149968-5",
      "email": "egodfree1w@arizona.edu",
      "phone": "2291087740",
      "address": "2686 Dahle Plaza",
      "suburb": "",
      "state": "",
      "postcode": "",
      "relatedContactId": [],
      "children": []
    },
    {
      "id": 70,
      "firstName": "Delmor",
      "lastName": "Ney",
      "dob": "1984-06-23",
      "crn": "848765169-0",
      "email": "dney1x@technorati.com",
      "phone": "3102178141",
      "address": "87666 Monica Point",
      "suburb": "",
      "state": "",
      "postcode": "",
      "relatedContactId": [],
      "children": []
    },
    {
      "id": 71,
      "firstName": "Birk",
      "lastName": "Caven",
      "dob": "2001-12-09",
      "crn": "399443839-X",
      "email": "bcaven1y@rediff.com",
      "phone": "3648354706",
      "address": "3630 Mendota Junction",
      "suburb": "",
      "state": "",
      "postcode": "",
      "relatedContactId": [],
      "children": []
    },
    {
      "id": 72,
      "firstName": "Toinette",
      "lastName": "Luthwood",
      "dob": "1992-05-17",
      "crn": "451958011-0",
      "email": "tluthwood1z@archive.org",
      "phone": "6693157324",
      "address": "1 Ridge Oak Hill",
      "suburb": "",
      "state": "",
      "postcode": "",
      "relatedContactId": [],
      "children": []
    },
    {
      "id": 73,
      "firstName": "Henrieta",
      "lastName": "Stellin",
      "dob": "1998-09-24",
      "crn": "531290663-8",
      "email": "hstellin20@google.ca",
      "phone": "2199377112",
      "address": "0 Leroy Street",
      "suburb": "",
      "state": "",
      "postcode": "",
      "relatedContactId": [],
      "children": []
    },
    {
      "id": 74,
      "firstName": "Valry",
      "lastName": "McCromley",
      "dob": "1998-08-09",
      "crn": "203799580-6",
      "email": "vmccromley21@amazon.de",
      "phone": "9313878376",
      "address": "49110 Russell Center",
      "suburb": "",
      "state": "",
      "postcode": "",
      "relatedContactId": [],
      "children": []
    },
    {
      "id": 75,
      "firstName": "Sigmund",
      "lastName": "Linneman",
      "dob": "1991-01-31",
      "crn": "392847289-5",
      "email": "slinneman22@gizmodo.com",
      "phone": "1029703734",
      "address": "07873 Monica Avenue",
      "suburb": "",
      "state": "",
      "postcode": "",
      "relatedContactId": [],
      "children": []
    },
    {
      "id": 76,
      "firstName": "Steward",
      "lastName": "McClune",
      "dob": "2003-09-21",
      "crn": "237038926-5",
      "email": "smcclune23@taobao.com",
      "phone": "4525029636",
      "address": "3462 Crowley Drive",
      "suburb": "",
      "state": "",
      "postcode": "",
      "relatedContactId": [],
      "children": []
    },
    {
      "id": 77,
      "firstName": "Tonya",
      "lastName": "Clancy",
      "dob": "1995-04-01",
      "crn": "607527122-8",
      "email": "tclancy24@eventbrite.com",
      "phone": "8381695519",
      "address": "2 Mayer Hill",
      "suburb": "",
      "state": "",
      "postcode": "",
      "relatedContactId": [],
      "children": []
    },
    {
      "id": 78,
      "firstName": "Lem",
      "lastName": "Norville",
      "dob": "2002-09-21",
      "crn": "164042751-1",
      "email": "lnorville25@linkedin.com",
      "phone": "8795071142",
      "address": "3 Texas Place",
      "suburb": "",
      "state": "",
      "postcode": "",
      "relatedContactId": [],
      "children": []
    },
    {
      "id": 79,
      "firstName": "Humbert",
      "lastName": "Diver",
      "dob": "1997-06-09",
      "crn": "180171268-9",
      "email": "hdiver26@gmpg.org",
      "phone": "5245369982",
      "address": "99019 Charing Cross Trail",
      "suburb": "",
      "state": "",
      "postcode": "",
      "relatedContactId": [],
      "children": []
    },
    {
      "id": 80,
      "firstName": "Jim",
      "lastName": "Artinstall",
      "dob": "1995-03-23",
      "crn": "387282892-4",
      "email": "jartinstall27@geocities.com",
      "phone": "7337180365",
      "address": "1 Mendota Alley",
      "suburb": "",
      "state": "",
      "postcode": "",
      "relatedContactId": [],
      "children": []
    },
    {
      "id": 81,
      "firstName": "Elvis",
      "lastName": "Whellans",
      "dob": "1996-12-19",
      "crn": "569345800-8",
      "email": "ewhellans28@bbc.co.uk",
      "phone": "3146639750",
      "address": "875 Red Cloud Alley",
      "suburb": "",
      "state": "",
      "postcode": "",
      "relatedContactId": [],
      "children": []
    },
    {
      "id": 82,
      "firstName": "Cobby",
      "lastName": "Iacovielli",
      "dob": "2002-06-11",
      "crn": "610137307-X",
      "email": "ciacovielli29@alibaba.com",
      "phone": "5438881717",
      "address": "179 Vera Park",
      "suburb": "",
      "state": "",
      "postcode": "",
      "relatedContactId": [],
      "children": []
    },
    {
      "id": 83,
      "firstName": "Gwendolin",
      "lastName": "McNuff",
      "dob": "1984-03-24",
      "crn": "107210056-8",
      "email": "gmcnuff2a@tiny.cc",
      "phone": "2416801909",
      "address": "0 Debs Park",
      "suburb": "",
      "state": "",
      "postcode": "",
      "relatedContactId": [],
      "children": []
    },
    {
      "id": 84,
      "firstName": "Dania",
      "lastName": "Mountain",
      "dob": "1980-10-20",
      "crn": "691460674-9",
      "email": "dmountain2b@google.co.jp",
      "phone": "9631243180",
      "address": "90540 Bay Circle",
      "suburb": "",
      "state": "",
      "postcode": "",
      "relatedContactId": [],
      "children": []
    },
    {
      "id": 85,
      "firstName": "Michaela",
      "lastName": "Chicchelli",
      "dob": "1998-06-30",
      "crn": "525940001-1",
      "email": "mchicchelli2c@goo.ne.jp",
      "phone": "9479854962",
      "address": "485 Kipling Terrace",
      "suburb": "",
      "state": "",
      "postcode": "",
      "relatedContactId": [],
      "children": []
    },
    {
      "id": 86,
      "firstName": "Orelie",
      "lastName": "Grotty",
      "dob": "1990-05-21",
      "crn": "615765647-6",
      "email": "ogrotty2d@state.tx.us",
      "phone": "9051894363",
      "address": "8664 Maywood Terrace",
      "suburb": "",
      "state": "",
      "postcode": "",
      "relatedContactId": [],
      "children": []
    },
    {
      "id": 87,
      "firstName": "Theda",
      "lastName": "Stead",
      "dob": "2003-05-26",
      "crn": "983050790-4",
      "email": "tstead2e@linkedin.com",
      "phone": "5324637493",
      "address": "0427 Muir Point",
      "suburb": "",
      "state": "",
      "postcode": "",
      "relatedContactId": [],
      "children": []
    },
    {
      "id": 88,
      "firstName": "Constanta",
      "lastName": "Corradetti",
      "dob": "2002-12-13",
      "crn": "756949573-X",
      "email": "ccorradetti2f@deliciousdays.com",
      "phone": "7177536871",
      "address": "50 Ronald Regan Avenue",
      "suburb": "",
      "state": "",
      "postcode": "",
      "relatedContactId": [],
      "children": []
    },
    {
      "id": 89,
      "firstName": "Danica",
      "lastName": "Novichenko",
      "dob": "1984-02-11",
      "crn": "282010879-2",
      "email": "dnovichenko2g@zimbio.com",
      "phone": "9536922579",
      "address": "517 Briar Crest Trail",
      "suburb": "",
      "state": "",
      "postcode": "",
      "relatedContactId": [],
      "children": []
    },
    {
      "id": 90,
      "firstName": "Ellynn",
      "lastName": "Crease",
      "dob": "2002-08-24",
      "crn": "735178365-9",
      "email": "ecrease2h@gizmodo.com",
      "phone": "5462439569",
      "address": "70 Lerdahl Center",
      "suburb": "",
      "state": "",
      "postcode": "",
      "relatedContactId": [],
      "children": []
    },
    {
      "id": 91,
      "firstName": "Burtie",
      "lastName": "Shevlane",
      "dob": "2002-07-12",
      "crn": "010304560-0",
      "email": "bshevlane2i@hc360.com",
      "phone": "8435710799",
      "address": "6591 Florence Pass",
      "suburb": "",
      "state": "",
      "postcode": "",
      "relatedContactId": [],
      "children": []
    },
    {
      "id": 92,
      "firstName": "Rad",
      "lastName": "Reany",
      "dob": "1996-03-01",
      "crn": "094536577-2",
      "email": "rreany2j@mlb.com",
      "phone": "2064087830",
      "address": "2881 Transport Plaza",
      "suburb": "",
      "state": "",
      "postcode": "",
      "relatedContactId": [],
      "children": []
    },
    {
      "id": 93,
      "firstName": "Doug",
      "lastName": "Montier",
      "dob": "1984-01-27",
      "crn": "645852368-8",
      "email": "dmontier2k@nature.com",
      "phone": "8792329445",
      "address": "371 Rockefeller Trail",
      "suburb": "",
      "state": "",
      "postcode": "",
      "relatedContactId": [],
      "children": []
    },
    {
      "id": 94,
      "firstName": "Brigham",
      "lastName": "Espinal",
      "dob": "1985-08-03",
      "crn": "324602814-1",
      "email": "bespinal2l@patch.com",
      "phone": "6792418637",
      "address": "14 Independence Parkway",
      "suburb": "",
      "state": "",
      "postcode": "",
      "relatedContactId": [],
      "children": []
    },
    {
      "id": 95,
      "firstName": "Wilhelmine",
      "lastName": "Wakes",
      "dob": "1981-07-03",
      "crn": "116766162-1",
      "email": "wwakes2m@elegantthemes.com",
      "phone": "4273729984",
      "address": "15 Crescent Oaks Junction",
      "suburb": "",
      "state": "",
      "postcode": "",
      "relatedContactId": [],
      "children": []
    },
    {
      "id": 96,
      "firstName": "Dennet",
      "lastName": "Angric",
      "dob": "1992-08-14",
      "crn": "274489210-6",
      "email": "dangric2n@pen.io",
      "phone": "1908126874",
      "address": "73 Buhler Crossing",
      "suburb": "",
      "state": "",
      "postcode": "",
      "relatedContactId": [],
      "children": []
    },
    {
      "id": 97,
      "firstName": "Mark",
      "lastName": "Sibthorpe",
      "dob": "1993-04-17",
      "crn": "292126995-3",
      "email": "msibthorpe2o@microsoft.com",
      "phone": "1108401245",
      "address": "284 Manley Parkway",
      "suburb": "",
      "state": "",
      "postcode": "",
      "relatedContactId": [],
      "children": []
    },
    {
      "id": 98,
      "firstName": "Lorena",
      "lastName": "Date",
      "dob": "1990-05-13",
      "crn": "814628119-2",
      "email": "ldate2p@mozilla.com",
      "phone": "9772008013",
      "address": "5865 American Alley",
      "suburb": "",
      "state": "",
      "postcode": "",
      "relatedContactId": [],
      "children": []
    },
    {
      "id": 99,
      "firstName": "Lindi",
      "lastName": "Deverson",
      "dob": "1980-09-24",
      "crn": "204206779-2",
      "email": "ldeverson2q@ucsd.edu",
      "phone": "8463582173",
      "address": "00092 Washington Terrace",
      "suburb": "",
      "state": "",
      "postcode": "",
      "relatedContactId": [],
      "children": []
    },
    {
      "id": 100,
      "firstName": "Aurilia",
      "lastName": "Mark",
      "dob": "1994-04-01",
      "crn": "645886365-9",
      "email": "amark2r@ifeng.com",
      "phone": "2834057674",
      "address": "3 Paget Street",
      "suburb": "",
      "state": "",
      "postcode": "",
      "relatedContactId": [],
      "children": []
    },
    {
      "id": 101,
      "firstName": "Larissa",
      "lastName": "Wilson",
      "email": "larissa.wilkinson@gmail.com",
      "phone": "+61403004358",
      "address": "3 Copson St"
    },
    {
      "id": 102,
      "firstName": "Larissa",
      "lastName": "Wilson",
      "email": "larissa.wilkinson@gmail.com",
      "phone": "+61403004358",
      "address": "3 Copson St"
    },
    {
      "id": 103,
      "firstName": "Larissa",
      "lastName": "Wilson",
      "email": "larissa.wilkinson@gmail.com",
      "phone": "+61403004358",
      "address": "3 Copson St"
    },
    {
      "id": 104,
      "firstName": "Junior",
      "lastName": "Bigoo",
      "email": "test@test.com",
      "phone": "0403004358",
      "address": "390A Main Rd, Glenorchy TAS 7010, Australia",
      "addressLat": -42.8327682,
      "addresssLng": 147.2732198
    }
  ]
}